[
  {
    "itemName": "mall_resource_1",
    "roiFront": "261,8,100,43",
    "roiBack": "261,8,100,43",
    "mode": "Quantity",
    "method": "Default",
    "keyword": "",
    "description": "左数第一个"
  },
  {
    "itemName": "mall_resource_2",
    "roiFront": "415,8,124,39",
    "roiBack": "415,8,124,39",
    "mode": "Quantity",
    "method": "Default",
    "keyword": "",
    "description": "左数第二个"
  },
  {
    "itemName": "mall_resource_3",
    "roiFront": "596,10,107,38",
    "roiBack": "596,10,107,38",
    "mode": "Quantity",
    "method": "Default",
    "keyword": "",
    "description": "左数第三个"
  },
  {
    "itemName": "mall_resource_4",
    "roiFront": "783,9,100,39",
    "roiBack": "783,9,100,39",
    "mode": "Quantity",
    "method": "Default",
    "keyword": "",
    "description": "左数第四个"
  },
  {
    "itemName": "mall_resource_5",
    "roiFront": "958,9,100,37",
    "roiBack": "958,9,100,37",
    "mode": "Quantity",
    "method": "Default",
    "keyword": "",
    "description": "左数第五个"
  },
  {
    "itemName": "mall_resource_6",
    "roiFront": "1129,6,100,41",
    "roiBack": "1129,6,100,41",
    "mode": "Quantity",
    "method": "Default",
    "keyword": "",
    "description": "左数第六个"
  },
  {
    "itemName": "mall_resource_7",
    "roiFront": "1100,54,150,38",
    "roiBack": "1100,54,150,38",
    "mode": "Quantity",
    "method": "Default",
    "keyword": "",
    "description": "左数第二排第一个"
  }
]